topsis/__init__.py
topsis/__main__.py
topsis_jasleen_102003238-0.1.dist-info/LICENSE.txt
topsis_jasleen_102003238-0.1.dist-info/METADATA
topsis_jasleen_102003238-0.1.dist-info/WHEEL
topsis_jasleen_102003238-0.1.dist-info/top_level.txt
topsis_jasleen_102003238-0.1.dist-info/RECORD
