Metadata-Version: 2.1
Name: topsis-jasleen-102003238
Version: 0.1
Summary: mplements topsis on the given input data file and generates topsis score and ranks accordingly.
Home-page: UNKNOWN
Author: jasleen phutela
Author-email: jphutela_be20@thapar.edu
License: UNKNOWN
Platform: UNKNOWN
Classifier: Programming Language :: Python :: 3
Classifier: License :: OSI Approved :: MIT License
Classifier: Operating System :: OS Independent
Requires-Python: >=3.6
